dsi_unit/__init__.py
dsi_unit/_warnings.py
dsi_unit/dsi_parser.py
dsi_unit/dsi_unit_node.py
dsi_unit/dsi_units.py
dsi_unit/regex_generator.py
dsi_unit/unit_mapping.py
dsiunits-3.1.0.dist-info/licenses/LICENSE
dsiunits-3.1.0.dist-info/METADATA
dsiunits-3.1.0.dist-info/WHEEL
dsiunits-3.1.0.dist-info/top_level.txt
dsiunits-3.1.0.dist-info/RECORD
