Metadata-Version: 2.4
Name: dsiUnits
Version: 3.1.0
Summary: This is a Python module for handling the SI units as objects in Python, parsing them from strings and converting them to Latex and Unicode, as well as performing math operations and calculating scale factors.
Author-email: Benedikt Seeger <benedikt.seeger@ptb.de>, Vanessa Stehr <vanessa.stehr@ptb.de>, Jaime Gonzalez Gomez <jaime.gonzalez-gomez@ptb.de>
License:                   GNU LESSER GENERAL PUBLIC LICENSE
Classifier: Programming Language :: Python :: 3
Classifier: License :: OSI Approved :: GNU Lesser General Public License v3 (LGPLv3)
Classifier: Operating System :: OS Independent
Requires-Python: >=3.9
License-File: LICENSE
Dynamic: license-file
